dao_scripts-1.5.10-py3.12-nspkg.pth
dao_analyzer/cache_scripts/__init__.py
dao_analyzer/cache_scripts/__main__.py
dao_analyzer/cache_scripts/_version.py
dao_analyzer/cache_scripts/argparser.py
dao_analyzer/cache_scripts/config.py
dao_analyzer/cache_scripts/endpoints.json
dao_analyzer/cache_scripts/logging.py
dao_analyzer/cache_scripts/main.py
dao_analyzer/cache_scripts/metadata.py
dao_analyzer/cache_scripts/aragon/__init__.py
dao_analyzer/cache_scripts/aragon/dao_names.json
dao_analyzer/cache_scripts/aragon/runner.py
dao_analyzer/cache_scripts/common/__init__.py
dao_analyzer/cache_scripts/common/api_requester.py
dao_analyzer/cache_scripts/common/blockscout.py
dao_analyzer/cache_scripts/common/common.py
dao_analyzer/cache_scripts/common/cryptocompare.py
dao_analyzer/cache_scripts/common/thegraph.py
dao_analyzer/cache_scripts/daohaus/__init__.py
dao_analyzer/cache_scripts/daohaus/runner.py
dao_analyzer/cache_scripts/daostack/__init__.py
dao_analyzer/cache_scripts/daostack/runner.py
dao_analyzer/cache_scripts/utils/__init__.py
dao_analyzer/cache_scripts/utils/uploadDataWarehouse.py
dao_scripts-1.5.10.dist-info/licenses/LICENSE
dao_scripts-1.5.10.dist-info/METADATA
dao_scripts-1.5.10.dist-info/WHEEL
dao_scripts-1.5.10.dist-info/entry_points.txt
dao_scripts-1.5.10.dist-info/namespace_packages.txt
dao_scripts-1.5.10.dist-info/top_level.txt
dao_scripts-1.5.10.dist-info/RECORD
