Metadata-Version: 2.4
Name: dao-scripts
Version: 1.5.10
Summary: "A tool to download data to monitor DAO activity"
Home-page: https://github.com/Grasia/dao-scripts
Author: David Davó
Author-email: ddavo@ucm.es
Project-URL: Source, https://github.com/Grasia/dao-scripts
Project-URL: Bug Tracker, https://github.com/Grasia/dao-scripts/issues
Project-URL: Changelog, https://github.com/Grasia/dao-scripts/blob/main/CHANGELOG.md
Classifier: Development Status :: 5 - Production/Stable
Classifier: Environment :: Console
Classifier: Intended Audience :: Science/Research
Classifier: License :: OSI Approved :: GNU General Public License v3 (GPLv3)
Classifier: Programming Language :: Python :: 3
Classifier: Programming Language :: Python :: 3.10
Classifier: Programming Language :: Python :: 3.11
Classifier: Programming Language :: Python :: 3.12
Classifier: Programming Language :: Python :: 3.13
Classifier: Programming Language :: Python :: 3.14
Classifier: Topic :: Sociology
Classifier: Typing :: Typed
Classifier: Topic :: Utilities
Requires-Python: >=3.10
License-File: LICENSE
Requires-Dist: dynaconf>=3.0.0
Requires-Dist: gql<4.0.0,>=3.0.0a1
Requires-Dist: numpy>=1.17.3
Requires-Dist: pandas>=1.3.4
Requires-Dist: portalocker>=2.3.2
Requires-Dist: pyarrow>=6.0.0
Requires-Dist: requests>=2.26.0
Requires-Dist: requests-cache>=0.8.1
Requires-Dist: requests-toolbelt>=0.9.1
Requires-Dist: tenacity>=8.0.0
Requires-Dist: tqdm>=4.62.3
Provides-Extra: upload
Requires-Dist: kaggle>=1.5.12; extra == "upload"
Requires-Dist: zenodo-client>=0.3.4; extra == "upload"
Provides-Extra: dev
Requires-Dist: build; extra == "dev"
Requires-Dist: pytest; extra == "dev"
Requires-Dist: hypothesis; extra == "dev"
Requires-Dist: flake8; extra == "dev"
Requires-Dist: pandas-vet; extra == "dev"
Requires-Dist: twine; extra == "dev"
Requires-Dist: hypothesis; extra == "dev"
Requires-Dist: pandas-vet; extra == "dev"
Dynamic: license-file
